Workbook

Sheet Summary
A1: Proposal Summary: Marlow Basin Water District RFP 2026-14
A2: Corvane Inspect, 3-year initial term. All values in US dollars. Prepared by Deal Desk, October 2026.
A4: Measure | B4: Value | C4: Calculation
A5: Base proposal (licenses, add-ons, services) | B5: ='Base Pricing'!$I$13 -> 658020 | C5: Base Pricing, 3-year total
A6: Gap closure (custom development) | B6: ='Gap Closure'!$F$11 -> 337500 | C6: Gap Closure, 3-year total
A7: Subtotal before discount | B7: =B5+B6 -> 995520 | C7: Base plus gap closure
A8: Subscription discount rate | B8: =Inputs!$B$9 -> 0 | C8: Inputs
A9: Discount amount | B9: =-'Base Pricing'!$I$14*B8 -> 0 | C9: Discount rate times 3-year user subscriptions
A10: Total proposal price (3 years) | B10: =B7+B9 -> 995520 | C10: Subtotal less discount
A11: District budget, not to exceed | B11: =Inputs!$B$8 -> 1150000 | C11: RFP Section 5
A12: Headroom under budget | B12: =B11-B10 -> 154480 | C12: Budget less total proposal price
A13: Within budget? | B13: =IF(B10<=B11,"Yes","No") -> Yes | C13: Proposals over budget may be non-responsive
A14: Discount approval needed | B14: =IF(B8>Inputs!$B$11,"Not allowed",IF(B8>Inputs!$B$10,"VP Sales","No approval needed")) -> No approval needed | C14: Pricing guardrails on Inputs
A17: Annual invoicing view (before discount)
A18: Year | B18: Amount ($) | C18: Notes
A19: Year 1 | B19: ='Base Pricing'!F13+SUM('Gap Closure'!D5:D10)+SUM('Gap Closure'!E5:E10) -> 616040 | C19: Includes all one-time fees
A20: Year 2 | B20: ='Base Pricing'!G13+SUM('Gap Closure'!E5:E10) -> 189740 | C20: Recurring only
A21: Year 3 | B21: ='Base Pricing'!H13+SUM('Gap Closure'!E5:E10) -> 189740 | C21: Recurring only
A22: Check: equals subtotal before discount | B22: =IF(ABS(SUM(B19:B21)-B7)<0.01,"OK","Mismatch") -> OK
A25: Discount scenarios
A26: Subscription discount | B26: Total price ($) | C26: Headroom under budget ($)
A27: 0 | B27: =B$7-'Base Pricing'!$I$14*A27 -> 995520 | C27: =B$11-B27 -> 154480
A28: 0.05 | B28: =B$7-'Base Pricing'!$I$14*A28 -> 975009 | C28: =B$11-B28 -> 174991
A29: 0.08 | B29: =B$7-'Base Pricing'!$I$14*A29 -> 962702.4 | C29: =B$11-B29 -> 187297.6
A30: 0.1 | B30: =B$7-'Base Pricing'!$I$14*A30 -> 954498 | C30: =B$11-B30 -> 195502
A31: 0.15 | B31: =B$7-'Base Pricing'!$I$14*A31 -> 933987 | C31: =B$11-B31 -> 216013
A33: Discounts above 10% need VP Sales approval; the maximum is 15% (FY27 guardrails).
A34: Fictional sample document for product demonstration. All names, organizations and figures are invented.

Sheet Inputs
A1: Inputs and Assumptions: MBWD RFP 2026-14
A2: Blue cells are inputs. Yellow cells are key assumptions that drive the proposal. Change inputs here only.
A4: Input | B4: Value | C4: Source or note
A5: Field users | B5: 240 | C5: RFP Section 1.2
A6: Office users | B6: 35 | C6: RFP Section 1.2
A7: Initial term (years) | B7: 3 | C7: RFP Section 5
A8: District budget, not to exceed (initial term) | B8: 1150000 | C8: RFP Section 5; includes all licenses, services and custom development
A9: Subscription discount offered | B9: 0 | C9: Applies to field and office user subscriptions only. Default 0%; see Discount Scenarios
A10: Discount requiring VP Sales approval (above) | B10: 0.1 | C10: Corvane pricing guardrail, FY27 price book
A11: Maximum discount allowed | B11: 0.15 | C11: Corvane pricing guardrail, FY27 price book
A12: Renewal price increase cap | B12: 0.04 | C12: RFP Section 5 (option years only)
A15: Fictional sample document for product demonstration. All names, organizations and figures are invented.

Sheet Base Pricing
A1: Base Proposal Pricing: Corvane Inspect for MBWD ($, 3-year initial term)
A2: Standard FY27 price book. Excludes custom development to close RFP gaps (see Gap Closure).
A4: Line item | B4: Type | C4: Qty | D4: Unit | E4: Unit price ($) | F4: Year 1 ($) | G4: Year 2 ($) | H4: Year 3 ($) | I4: 3-year total ($) | J4: RFP reference
A5: Field user subscription | B5: Subscription | C5: =Inputs!$B$5 -> 240 | D5: per user per month | E5: 38 | F5: =C5*E5*12 -> 109440 | G5: =F5 -> 109440 | H5: =G5 -> 109440 | I5: =SUM(F5:H5) -> 328320 | J5: R-01 to R-12
A6: Office user subscription | B6: Subscription | C6: =Inputs!$B$6 -> 35 | D6: per user per month | E6: 65 | F6: =C6*E6*12 -> 27300 | G6: =F6 -> 27300 | H6: =G6 -> 27300 | I6: =SUM(F6:H6) -> 81900 | J6: Web console users
A7: GIS Connector add-on (Esri ArcGIS) | B7: Add-on | C7: 1 | D7: per year | E7: 9000 | F7: =C7*E7 -> 9000 | G7: =F7 -> 9000 | H7: =G7 -> 9000 | I7: =SUM(F7:H7) -> 27000 | J7: R-04
A8: Maximo Connector add-on | B8: Add-on | C8: 1 | D8: per year | E8: 12000 | F8: =C8*E8 -> 12000 | G8: =F8 -> 12000 | H8: =G8 -> 12000 | I8: =SUM(F8:H8) -> 36000 | J8: R-05
A9: Archive add-on (10-year retention) | B9: Add-on | C9: 1 | D9: per year | E9: 14000 | F9: =C9*E9 -> 14000 | G9: =F9 -> 14000 | H9: =G9 -> 14000 | I9: =SUM(F9:H9) -> 42000 | J9: R-19 (default retention is 5 years)
A10: Implementation and data migration | B10: One-time | C10: 1 | D10: fixed fee | E10: 96000 | F10: =C10*E10 -> 96000 | G10: 0 | H10: 0 | I10: =SUM(F10:H10) -> 96000 | J10: Section 3, R-24
A11: Train-the-trainer program | B11: One-time | C11: 1 | D11: fixed fee | E11: 18000 | F11: =C11*E11 -> 18000 | G11: 0 | H11: 0 | I11: =SUM(F11:H11) -> 18000 | J11: R-23
A12: On-site field training sessions | B12: One-time | C12: 12 | D12: per session | E12: 2400 | F12: =C12*E12 -> 28800 | G12: 0 | H12: 0 | I12: =SUM(F12:H12) -> 28800 | J12: R-23
A13: Base proposal total | F13: =SUM(F5:F12) -> 314540 | G13: =SUM(G5:G12) -> 171740 | H13: =SUM(H5:H12) -> 171740 | I13: =SUM(I5:I12) -> 658020
A14: of which: user subscriptions (discountable) | I14: =SUMIFS(I5:I12,B5:B12,"Subscription") -> 410220
A16: Note: unit prices are FY27 list prices. Subscriptions are invoiced annually in advance; one-time fees against milestones (RFP Section 5).
A17: Fictional sample document for product demonstration. All names, organizations and figures are invented.

Sheet Gap Closure
A1: Gap Closure: custom development to meet Mandatory RFP requirements ($)
A2: Engineering estimates from Product Management, September 2026. Priced to the District as custom development line items.
A4: RFP req. | B4: Gap in Corvane Inspect 6.2 | C4: Approach to close | D4: One-time ($) | E4: Annual ($) | F4: 3-year total ($) | G4: Delivery | H4: Owner | I4: Status
A5: R-06 | B5: Offline window is 24 hours; RFP requires 72 hours | C5: Extend offline cache and lock window to 96 hours (configurable) | D5: 85000 | E5: 0 | F5: =D5+E5*Inputs!$B$7 -> 85000 | G5: 14 weeks from award | H5: Priya Raman | I5: Estimate; engineering to confirm by Oct 8
A6: R-10 | B6: UI is English only; RFP requires Spanish UI | C6: Accelerate Spanish UI from release 7.0 for MBWD go-live | D6: 32000 | E6: 0 | F6: =D6+E6*Inputs!$B$7 -> 32000 | G6: Before go-live | H6: Priya Raman | I6: Committed on roadmap; acceleration fee
A7: R-10 | B7: District forms need Spanish content | C7: Translate and configure 35 District form templates | D7: 6500 | E7: 0 | F7: =D7+E7*Inputs!$B$7 -> 6500 | G7: During configuration | H7: Implementation team | I7: Fixed fee
A8: R-14 | B8: No SCIM 2.0; manual or CSV deprovisioning | C8: Accelerate SCIM 2.0 provisioning connector | D8: 40000 | E8: 0 | F8: =D8+E8*Inputs!$B$7 -> 40000 | G8: 12 weeks from award | H8: Priya Raman | I8: Not committed on roadmap; needs VP Eng sign-off
A9: R-17 | B9: Vendor-managed keys only; RFP requires customer-managed keys | C9: Customer-managed key integration plus dedicated key hosting | D9: 120000 | E9: 18000 | F9: =D9+E9*Inputs!$B$7 -> 174000 | G9: 16 weeks from award | H9: Engineering | I9: Under evaluation; highest risk item
A10: R-20 | B10: Incident notice is 5 business days; RFP requires 72 hours | C10: Contract amendment to 72-hour notification for MBWD | D10: 0 | E10: 0 | F10: =D10+E10*Inputs!$B$7 -> 0 | G10: At contract | H10: Lena Ortiz | I10: Needs Legal and Security Ops approval
B11: Total gap closure | D11: =SUM(D5:D10) -> 283500 | E11: =SUM(E5:E10) -> 18000 | F11: =SUM(F5:F10) -> 337500
B13: Not costed: R-25 (10-hour shift battery, Desirable). Low-power location mode ships in 6.3, Q1 2027, at no charge.
B14: Fictional sample document for product demonstration. All names, organizations and figures are invented.
